software_package_RK_BE103_Caltech/ECDF.py
software_package_RK_BE103_Caltech/__init__.py
software_package_RK_BE103_Caltech/labeling_ecdf_comparison.py
software_package_RK_BE103_Caltech-0.0.2.dist-info/LICENSE.txt
software_package_RK_BE103_Caltech-0.0.2.dist-info/METADATA
software_package_RK_BE103_Caltech-0.0.2.dist-info/WHEEL
software_package_RK_BE103_Caltech-0.0.2.dist-info/top_level.txt
software_package_RK_BE103_Caltech-0.0.2.dist-info/RECORD
